pyuseragents/__init__.py
pyuseragents/_backward_compatibility.py
pyuseragents/_useragents.py
pyuseragents/data/__init__.py
pyuseragents/data/list.py
pyuseragents-1.0.5.dist-info/LICENSE
pyuseragents-1.0.5.dist-info/METADATA
pyuseragents-1.0.5.dist-info/WHEEL
pyuseragents-1.0.5.dist-info/top_level.txt
pyuseragents-1.0.5.dist-info/RECORD
