Metadata-Version: 2.1
Name: pyuseragents
Version: 1.0.5
Summary: A Python module which does one thing: giving you a random User-Agent Header
Home-page: https://github.com/Animenosekai/useragents
Author: Anime no Sekai
Author-email: niichannomail@gmail.com
License: MIT
Download-URL: https://github.com/Animenosekai/useragents/archive/v1.0.5.tar.gz
Keywords: python,useragents,ua,user-agents,user-agent,http,request,header,http-header
Platform: UNKNOWN
Classifier: Development Status :: 5 - Production/Stable
Classifier: License :: OSI Approved :: MIT License
Classifier: Programming Language :: Python :: 2
Classifier: Programming Language :: Python :: 3
